[
  { "year": 1913, "avg_cpi": 9.9 },
  { "year": 1914, "avg_cpi": 10.0 },
  { "year": 1915, "avg_cpi": 10.1 },
  { "year": 1916, "avg_cpi": 10.9 },
  { "year": 1917, "avg_cpi": 12.8 },
  { "year": 1918, "avg_cpi": 15.0 },
  { "year": 1919, "avg_cpi": 17.3 },
  { "year": 1920, "avg_cpi": 20.0 },
  { "year": 1921, "avg_cpi": 17.9 },
  { "year": 1922, "avg_cpi": 16.8 },
  { "year": 1923, "avg_cpi": 17.1 },
  { "year": 1924, "avg_cpi": 17.1 },
  { "year": 1925, "avg_cpi": 17.5 },
  { "year": 1926, "avg_cpi": 17.7 },
  { "year": 1927, "avg_cpi": 17.4 },
  { "year": 1928, "avg_cpi": 17.2 },
  { "year": 1929, "avg_cpi": 17.2 },
  { "year": 1930, "avg_cpi": 16.7 },
  { "year": 1931, "avg_cpi": 15.2 },
  { "year": 1932, "avg_cpi": 13.6 },
  { "year": 1933, "avg_cpi": 12.9 },
  { "year": 1934, "avg_cpi": 13.4 },
  { "year": 1935, "avg_cpi": 13.7 },
  { "year": 1936, "avg_cpi": 13.9 },
  { "year": 1937, "avg_cpi": 14.4 },
  { "year": 1938, "avg_cpi": 14.1 },
  { "year": 1939, "avg_cpi": 13.9 },
  { "year": 1940, "avg_cpi": 14.0 },
  { "year": 1941, "avg_cpi": 14.7 },
  { "year": 1942, "avg_cpi": 16.3 },
  { "year": 1943, "avg_cpi": 17.3 },
  { "year": 1944, "avg_cpi": 17.6 },
  { "year": 1945, "avg_cpi": 18.0 },
  { "year": 1946, "avg_cpi": 19.5 },
  { "year": 1947, "avg_cpi": 22.3 },
  { "year": 1948, "avg_cpi": 24.0 },
  { "year": 1949, "avg_cpi": 23.8 },
  { "year": 1950, "avg_cpi": 24.1 },
  { "year": 1951, "avg_cpi": 26.0 },
  { "year": 1952, "avg_cpi": 26.6 },
  { "year": 1953, "avg_cpi": 26.8 },
  { "year": 1954, "avg_cpi": 26.9 },
  { "year": 1955, "avg_cpi": 26.8 },
  { "year": 1956, "avg_cpi": 27.2 },
  { "year": 1957, "avg_cpi": 28.1 },
  { "year": 1958, "avg_cpi": 28.9 },
  { "year": 1959, "avg_cpi": 29.2 },
  { "year": 1960, "avg_cpi": 29.6 },
  { "year": 1961, "avg_cpi": 29.9 },
  { "year": 1962, "avg_cpi": 30.3 },
  { "year": 1963, "avg_cpi": 30.6 },
  { "year": 1964, "avg_cpi": 31.0 },
  { "year": 1965, "avg_cpi": 31.5 },
  { "year": 1966, "avg_cpi": 32.5 },
  { "year": 1967, "avg_cpi": 33.4 },
  { "year": 1968, "avg_cpi": 34.8 },
  { "year": 1969, "avg_cpi": 36.7 },
  { "year": 1970, "avg_cpi": 38.8 },
  { "year": 1971, "avg_cpi": 40.5 },
  { "year": 1972, "avg_cpi": 41.8 },
  { "year": 1973, "avg_cpi": 44.4 },
  { "year": 1974, "avg_cpi": 49.3 },
  { "year": 1975, "avg_cpi": 53.8 },
  { "year": 1976, "avg_cpi": 56.9 },
  { "year": 1977, "avg_cpi": 60.6 },
  { "year": 1978, "avg_cpi": 65.2 },
  { "year": 1979, "avg_cpi": 72.6 },
  { "year": 1980, "avg_cpi": 82.4 },
  { "year": 1981, "avg_cpi": 90.9 },
  { "year": 1982, "avg_cpi": 96.5 },
  { "year": 1983, "avg_cpi": 99.6 },
  { "year": 1984, "avg_cpi": 103.9 },
  { "year": 1985, "avg_cpi": 107.6 },
  { "year": 1986, "avg_cpi": 109.6 },
  { "year": 1987, "avg_cpi": 113.6 },
  { "year": 1988, "avg_cpi": 118.3 },
  { "year": 1989, "avg_cpi": 124.0 },
  { "year": 1990, "avg_cpi": 130.7 },
  { "year": 1991, "avg_cpi": 136.2 },
  { "year": 1992, "avg_cpi": 140.3 },
  { "year": 1993, "avg_cpi": 144.5 },
  { "year": 1994, "avg_cpi": 148.2 },
  { "year": 1995, "avg_cpi": 152.4 },
  { "year": 1996, "avg_cpi": 156.9 },
  { "year": 1997, "avg_cpi": 160.5 },
  { "year": 1998, "avg_cpi": 163.0 },
  { "year": 1999, "avg_cpi": 166.6 },
  { "year": 2000, "avg_cpi": 172.2 },
  { "year": 2001, "avg_cpi": 177.1 },
  { "year": 2002, "avg_cpi": 179.9 },
  { "year": 2003, "avg_cpi": 184.0 },
  { "year": 2004, "avg_cpi": 188.9 },
  { "year": 2005, "avg_cpi": 195.3 },
  { "year": 2006, "avg_cpi": 201.6 },
  { "year": 2007, "avg_cpi": 207.3 },
  { "year": 2008, "avg_cpi": 215.3 },
  { "year": 2009, "avg_cpi": 214.5 },
  { "year": 2010, "avg_cpi": 218.1 },
  { "year": 2011, "avg_cpi": 224.9 },
  { "year": 2012, "avg_cpi": 229.6 },
  { "year": 2013, "avg_cpi": 233.0 },
  { "year": 2014, "avg_cpi": 236.7 },
  { "year": 2015, "avg_cpi": 237.0 },
  { "year": 2016, "avg_cpi": 240.0 },
  { "year": 2017, "avg_cpi": 245.1 },
  { "year": 2018, "avg_cpi": 251.1 },
  { "year": 2019, "avg_cpi": 255.7 },
  { "year": 2020, "avg_cpi": 258.8 },
  { "year": 2021, "avg_cpi": 271.0 },
  { "year": 2022, "avg_cpi": 292.7 },
  { "year": 2023, "avg_cpi": 304.7 }
]
